django_magic_authorization/__init__.py
django_magic_authorization/admin.py
django_magic_authorization/apps.py
django_magic_authorization/middleware.py
django_magic_authorization/migrations/0001_initial.py
django_magic_authorization/migrations/__init__.py
django_magic_authorization/models.py
django_magic_authorization/urls.py
django_magic_authorization-0.1.4.dist-info/WHEEL
django_magic_authorization-0.1.4.dist-info/METADATA
django_magic_authorization-0.1.4.dist-info/RECORD
