Metadata-Version: 2.3
Name: django-magic-authorization
Version: 0.1.4
Summary: Add magic authorization links to your django project.
Keywords: django,authorization,access-control,middleware
Author: j23n
Author-email: j23n <oss@j23n.com>
License: BSD 3-Clause License
Classifier: Development Status :: 3 - Alpha
Classifier: Environment :: Web Environment
Classifier: Framework :: Django
Classifier: Framework :: Django :: 5.2
Classifier: Intended Audience :: Developers
Classifier: Operating System :: OS Independent
Classifier: Programming Language :: Python
Classifier: Programming Language :: Python :: 3
Classifier: Programming Language :: Python :: 3.12
Classifier: Programming Language :: Python :: 3.13
Classifier: Topic :: Software Development :: Libraries :: Python Modules
Requires-Dist: django>=5.2
Requires-Python: >=3.10
Project-URL: Bug Tracker, https://codeberg.org/j23n/django-magic-authorization/issues
Project-URL: Changelog, https://codeberg.org/j23n/django-magic-authorization/src/branch/master/CHANGELOG.md
Project-URL: Homepage, https://codeberg.org/j23n/django-magic-authorization
Project-URL: Repository, https://codeberg.org/j23n/django-magic-authorization
